[{"id": 1,"guid": "40c689b4-0e15-4115-8816-40bff619d859","wall_id": 1,"group_id": 1,"status": 1,"super_admin": 1,"username": "admin","email": "ctembreull@roosterpark.com","auth_mode": "local","tags": "abc","language": "en","last_activity_email": "2015-04-13 21:06:40","created_at": "2015-04-13 21:06:40","created_by": null,"updated_at": "2015-05-22 18:34:29","updated_by": 1,"last_login": "2015-05-22 21:22:55","visibility": 1}, {"id": 2,"guid": "391656b7-e3e8-43c5-9b53-bc5f90df6c95","wall_id": 3,"group_id": 1,"status": 1,"super_admin": 0,"username": "ctembreull","email": "chris@tembreull.org","auth_mode": "local","tags": "Software Development, System Administration, DevOps, RESTful Design, Programming","language": "en","last_activity_email": "2015-04-14 17:47:11","created_at": "2015-04-14 17:47:11","created_by": 1,"updated_at": "2015-05-22 18:36:50","updated_by": 1,"last_login": "2015-04-24 22:58:36","visibility": 1}, {"id": 3,"guid": "72bd6d8a-e849-4103-932a-3246b0ed9366","wall_id": 4,"group_id": 1,"status": 1,"super_admin": 0,"username": "scott","email": "scott@roosterpark.com","auth_mode": "local","tags": "Promotions,Process Improvement,Revenue,Human resources,Powerpoint,Innovation,Microsoft Word,Employees,Customer Service,Budgets","language": null,"last_activity_email": "2015-04-17 20:51:11","created_at": "2015-04-17 20:51:11","created_by": 1,"updated_at": "2015-05-01 00:41:08","updated_by": 1,"last_login": "2015-04-20 19:45:56","visibility": 1}, {"id": 4,"guid": "191e05d9-9254-417b-ae71-e01b48da22a1","wall_id": 5,"group_id": 1,"status": 1,"super_admin": 0,"username": "brysmi","email": "bryans@roosterpark.com","auth_mode": "local","tags": "Software Development,Web Applications,Start-ups,Software Engineering,Agile Methodologies,Program Management,Product Development,JavaScript,Leadership,Product Management,Entrepreneurship,Cloud Computing,Emerging Technologies,Business Modeling,jQuery,Product Incubation,Business Strategy,Facebook API,HTML 5,Social Media Marketing,Early Adoption,LAMP,CSS3,Marketing Strategy,New Business Development,Social Networking,Software Product Management,Film,Browser Extensions,Decision Support Models,Marketing,Marketing of Innovations,Global Strategy,Strategic Management,Lean Startup,App Store Marketing,Application Lifecycle Management,Facebook Social Graph,HTML5,Product Marketing...,Social Media Consultant,Social Media Engagement,Social Media APIs,Software Systems,Technical Program Management,Thought Leadership,Semantic Technologies,iOS App Management,iOS App Marketing","language": null,"last_activity_email": "2015-04-17 20:51:43","created_at": "2015-04-17 20:51:43","created_by": 1,"updated_at": "2015-05-01 00:32:35","updated_by": 4,"last_login": "2015-05-01 00:16:38","visibility": 1}, {"id": 5,"guid": "9246c47f-9934-40cd-8311-974370282645","wall_id": 6,"group_id": 1,"status": 1,"super_admin": 0,"username": "joeedens","email": "joe@roosterpark.com","auth_mode": "local","tags": "design, web design, user experience, front-end development, HTML, CSS","language": "en","last_activity_email": "2015-04-17 20:52:46","created_at": "2015-04-17 20:52:46","created_by": 1,"updated_at": "2015-05-13 21:54:00","updated_by": 5,"last_login": "2015-05-13 21:53:42","visibility": 1}, {"id": 7,"guid": "4be03a06-10d8-4aca-8d67-d3f5502f479a","wall_id": 8,"group_id": 1,"status": 1,"super_admin": 1,"username": "sage","email": "sage@roosterpark.com","auth_mode": "local","tags": "Start-ups, Strategy, Leadership, Partnerships, Entrepreneurship, Business Strategy, Planning","language": "en","last_activity_email": "2015-04-17 20:55:58","created_at": "2015-04-17 20:55:58","created_by": 1,"updated_at": "2015-05-22 21:12:33","updated_by": 26,"last_login": "2015-05-22 21:12:33","visibility": 1}, {"id": 8,"guid": "d93fd5eb-b0d1-4097-bd54-b08e6cb299f7","wall_id": 9,"group_id": 1,"status": 1,"super_admin": 0,"username": "dalterma","email": "dalterma@c4c.edu","auth_mode": "local","tags": "Software, Vendors, Communication, Applications, Leadership, social media, Designs, Sales Management, Management, Commercial Real Estate, Research, Process Improvement, accounting, Analysis, Sales, Strategy","language": null,"last_activity_email": "2015-04-20 05:31:50","created_at": "2015-04-20 05:31:50","created_by": 1,"updated_at": "2015-05-01 00:51:25","updated_by": 1,"last_login": "2015-04-20 20:08:43","visibility": 1}, {"id": 9,"guid": "f0fd8921-9537-4e5f-a584-1fc613bf092c","wall_id": 10,"group_id": 1,"status": 1,"super_admin": 0,"username": "fbohrer","email": "fbohrer@c4c.edu","auth_mode": "local","tags": "social media, International, Events, Heavy Equipment, Powerpoint, Engineering, Teaching, Problem Solving, Offices, Employees, Consulting, Sales, Communication, Real Estate, Project Planning","language": null,"last_activity_email": "2015-04-20 05:33:43","created_at": "2015-04-20 05:33:43","created_by": 1,"updated_at": "2015-05-01 00:51:45","updated_by": 1,"last_login": "2015-04-20 20:09:41","visibility": 1}, {"id": 10,"guid": "241c3785-278a-4794-8730-76b371ee20cb","wall_id": 11,"group_id": 1,"status": 1,"super_admin": 0,"username": "dbrown","email": "dbrown@c4c.edu","auth_mode": "local","tags": "Legal, Sales Management, Healthcare, Budgets, Communication, Writing, Human resources, Microsoft Office, Product Development, Compliance, Public speaking, Editing, Design","language": null,"last_activity_email": "2015-04-20 05:35:05","created_at": "2015-04-20 05:35:05","created_by": 1,"updated_at": "2015-05-01 00:53:05","updated_by": 1,"last_login": "2015-04-20 20:10:31","visibility": 1}, {"id": 11,"guid": "451d618a-cb02-4c9b-a340-9eecfa5551e0","wall_id": 12,"group_id": 1,"status": 1,"super_admin": 0,"username": "rbuckmas","email": "rbuckmas@c4c.edu","auth_mode": "local","tags": "Product Development, Compliance, Public speaking, Editing, Designs, Microsoft Word, New business development, Problem Solving, Policy, Databases, Real Estate","language": null,"last_activity_email": "2015-04-20 05:36:28","created_at": "2015-04-20 05:36:28","created_by": 1,"updated_at": "2015-05-01 00:53:03","updated_by": 1,"last_login": "2015-04-20 20:11:09","visibility": 1}, {"id": 12,"guid": "cb2f9ed0-30df-49a3-b347-ec9f71b2153a","wall_id": 13,"group_id": 1,"status": 1,"super_admin": 0,"username": "ldorsey","email": "ldorsey@c4c.edu","auth_mode": "local","tags": "Databases, Real Estate, Construction, Applications, Teaching, Training, Information Technology, Advertising","language": null,"last_activity_email": "2015-04-20 05:37:54","created_at": "2015-04-20 05:37:54","created_by": 1,"updated_at": "2015-05-01 00:53:00","updated_by": 1,"last_login": "2015-04-24 22:18:54","visibility": 1}, {"id": 13,"guid": "b047802d-5bbf-4ac6-9090-b7ffac8e64ec","wall_id": 14,"group_id": 1,"status": 1,"super_admin": 0,"username": "gdykstra","email": "gdykstra@c4c.edu","auth_mode": "local","tags": "Advertising, Presentations, Sales, Customer Service, Software, Project Management, Innovation, International, Mentoring, Auditing, Research, Manufacturing, Finance, Databases, Real Estate, Construction, Applications, Teaching, Training, Information Technology, Advertising","language": null,"last_activity_email": "2015-04-20 05:47:17","created_at": "2015-04-20 05:47:17","created_by": 1,"updated_at": "2015-05-01 00:52:58","updated_by": 1,"last_login": "2015-04-20 20:13:47","visibility": 1}, {"id": 14,"guid": "7166fc4c-041a-4518-a1a6-ab998a7f1f2e","wall_id": 15,"group_id": 1,"status": 1,"super_admin": 0,"username": "roieisen","email": "roieisen@c4c.edu","auth_mode": "local","tags": "Applications, Teaching, Training, Information Technology, Advertising, Presentations, Sales, Business Strategy, Testing, Management, Team Building, Materials, Cost, Computer Program, Time Management","language": null,"last_activity_email": "2015-04-20 05:49:03","created_at": "2015-04-20 05:49:03","created_by": 1,"updated_at": "2015-05-01 00:52:57","updated_by": 1,"last_login": "2015-04-20 20:14:26","visibility": 1}, {"id": 15,"guid": "6295769d-488a-41af-b047-fcbaa12e592c","wall_id": 16,"group_id": 1,"status": 1,"super_admin": 0,"username": "jmgennis","email": "jmgennis@c4c.edu","auth_mode": "local","tags": "Writing, Human resources, Microsoft Office, Product Development, Compliance, Public speaking, Editing, Designs, Microsoft Word, New business development, Problem Solving","language": null,"last_activity_email": "2015-04-20 05:50:07","created_at": "2015-04-20 05:50:07","created_by": 1,"updated_at": "2015-05-01 00:52:35","updated_by": 1,"last_login": "2015-04-20 20:18:36","visibility": 1}, {"id": 16,"guid": "5f8331a0-4f13-4218-915c-2296ce7b79a7","wall_id": 17,"group_id": 1,"status": 1,"super_admin": 0,"username": "argraham","email": "argraham@c4c.edu","auth_mode": "local","tags": "Innovation, International, Mentoring, Consulting, Business Strategy, Testing, Management, Team Building, Materials, Cost, Computer Program, Time Management, Strategic Planning, Auditing, Research, Manufacturing, Finance","language": null,"last_activity_email": "2015-04-20 05:51:00","created_at": "2015-04-20 05:51:00","created_by": 1,"updated_at": "2015-05-01 00:52:37","updated_by": 1,"last_login": "2015-04-20 20:19:26","visibility": 1}, {"id": 17,"guid": "582ece2f-166f-47d8-9f12-f7dfc1caa5da","wall_id": 18,"group_id": 1,"status": 1,"super_admin": 0,"username": "dhanson","email": "dhanson@c4c.edu","auth_mode": "local","tags": "Editing, Designs, Microsoft Word, New business development, Problem Solving, Policy, Databases, Real Estate, Construction","language": null,"last_activity_email": "2015-04-20 05:52:32","created_at": "2015-04-20 05:52:32","created_by": 1,"updated_at": "2015-05-01 00:52:43","updated_by": 1,"last_login": "2015-04-20 20:20:03","visibility": 1}, {"id": 18,"guid": "0aaae96f-c451-49c9-82a4-823235c9a2e7","wall_id": 19,"group_id": 1,"status": 1,"super_admin": 0,"username": "fbholt","email": "fbholt@c4c.edu","auth_mode": "local","tags": "Policy, Databases, Real Estate, Construction, Applications, Teaching, Training, Information Technology, Advertising, Presentations, Sales","language": null,"last_activity_email": "2015-04-20 05:53:29","created_at": "2015-04-20 05:53:29","created_by": 1,"updated_at": "2015-05-01 00:52:42","updated_by": 1,"last_login": "2015-04-20 20:23:41","visibility": 1}, {"id": 19,"guid": "e916ecff-0ae4-449d-917b-9c45ff4256da","wall_id": 20,"group_id": 1,"status": 1,"super_admin": 0,"username": "cti2","email": "cti2@c4c.edu","auth_mode": "local","tags": "Applications, Teaching, Training, Information Technology, Advertising, Presentations, Sales, Customer Service, Business Services, Vendors, Analysis, Performance Tuning, Events, Heavy Equipment, Software, Project Management, Innovation, International, Mentoring","language": null,"last_activity_email": "2015-04-20 05:56:01","created_at": "2015-04-20 05:56:01","created_by": 1,"updated_at": "2015-05-01 00:52:45","updated_by": 1,"last_login": "2015-04-20 20:22:55","visibility": 1}, {"id": 20,"guid": "c907e701-2d10-49d4-981a-e4c5a4350677","wall_id": 21,"group_id": 1,"status": 1,"super_admin": 0,"username": "vjandhyala","email": "vj@c4c.edu","auth_mode": "local","tags": "Policy, Databases, Real Estate, Construction, Applications, Teaching, Training, Information Technology","language": null,"last_activity_email": "2015-04-20 05:57:50","created_at": "2015-04-20 05:57:50","created_by": 1,"updated_at": "2015-05-01 00:52:47","updated_by": 1,"last_login": "2015-04-20 20:21:24","visibility": 1}, {"id": 21,"guid": "fe9fac27-4df5-4338-aee9-1c7066fe2a8e","wall_id": 22,"group_id": 1,"status": 1,"super_admin": 0,"username": "jordancm","email": "jordancm@c4c.edu","auth_mode": "local","tags": "Management, Data, Program Management, Project Planning, New business development, Product Development, Human Resources, Heavy Equipment, Order Fulfillment, Finance","language": null,"last_activity_email": "2015-04-20 05:59:19","created_at": "2015-04-20 05:59:19","created_by": 1,"updated_at": "2015-05-01 00:52:55","updated_by": 1,"last_login": "2015-04-20 20:22:18","visibility": 1}, {"id": 22,"guid": "3d122f3a-4681-4c6b-92a8-824290028ca5","wall_id": 23,"group_id": 1,"status": 1,"super_admin": 0,"username": "jkindra","email": "jkindra@c4c.edu","auth_mode": "local","tags": "Events, Mentoring, Negotiation, Innovation, Recruiting, International, Engineering, Education, Change management","language": null,"last_activity_email": "2015-04-20 06:00:23","created_at": "2015-04-20 06:00:23","created_by": 1,"updated_at": "2015-05-01 00:52:54","updated_by": 1,"last_login": "2015-04-20 20:22:35","visibility": 1}, {"id": 23,"guid": "ba502dda-cdd9-4038-bb2b-72948de10437","wall_id": 24,"group_id": 1,"status": 1,"super_admin": 0,"username": "kenmyer","email": "kenmyer@c4c.edu","auth_mode": "local","tags": "Technology Executive, Strategy, Fortune 100, Leadership, Start-ups, Strategic Partnerships, Mergers","language": "en","last_activity_email": "2015-04-20 21:08:56","created_at": "2015-04-20 21:08:56","created_by": 1,"updated_at": "2015-04-24 20:23:48","updated_by": 1,"last_login": "2015-04-20 23:48:35","visibility": 1}, {"id": 24,"guid": "adcafdaa-e640-4c14-99ab-495a6898aec7","wall_id": 25,"group_id": 1,"status": 1,"super_admin": 0,"username": "Salvia","email": "sage+hh2@roosterpark.com","auth_mode": "local","tags": "Engineering,Education,Change management,Organization,Offices,social media,Strategic Planning,Writing,Windows,Powerpoint","language": "en","last_activity_email": "2015-04-28 22:42:58","created_at": "2015-04-28 22:42:58","created_by": null,"updated_at": "2015-05-01 00:52:52","updated_by": 1,"last_login": "2015-04-28 22:42:58","visibility": 1}, {"id": 26,"guid": "2b077319-c507-4a43-8251-46cd65ce2a9e","wall_id": 27,"group_id": 1,"status": 1,"super_admin": 1,"username": "mclarke","email": "mclarke@uw.edu","auth_mode": "local","tags": "","language": "en","last_activity_email": "2015-04-29 21:28:21","created_at": "2015-04-29 21:28:21","created_by": null,"updated_at": "2015-05-22 21:09:37","updated_by": 1,"last_login": "2015-05-22 21:09:37","visibility": 1}, {"id": 29,"guid": "78d70f1e-9dc3-496f-9f44-6a4e96f56366","wall_id": 40,"group_id": 1,"status": 1,"super_admin": 0,"username": "daekwon","email": "daekwon@uwc4c.com","auth_mode": "local","tags": null,"language": null,"last_activity_email": "2015-05-21 21:05:43","created_at": "2015-05-21 21:05:43","created_by": 26,"updated_at": "2015-05-22 06:04:24","updated_by": 26,"last_login": "2015-05-21 21:07:03","visibility": 1}, {"id": 30,"guid": "fcacd21f-4e4b-43f1-bfe0-8624ec962cdb","wall_id": 41,"group_id": 1,"status": 1,"super_admin": 0,"username": "scottbright","email": "scottbright@uwc4c.com","auth_mode": "local","tags": null,"language": null,"last_activity_email": "2015-05-21 21:18:28","created_at": "2015-05-21 21:18:28","created_by": 26,"updated_at": "2015-05-21 21:18:28","updated_by": 26,"last_login": "2015-05-21 22:46:31","visibility": 1}, {"id": 31,"guid": "29711984-e323-4465-9f35-6cf27b2710d1","wall_id": 42,"group_id": 1,"status": 1,"super_admin": 0,"username": "dianeha","email": "dianeha@uwc4c.com","auth_mode": "local","tags": null,"language": null,"last_activity_email": "2015-05-21 21:22:27","created_at": "2015-05-21 21:22:27","created_by": 26,"updated_at": "2015-05-22 06:06:24","updated_by": 26,"last_login": "2015-05-21 21:22:49","visibility": 1}, {"id": 32,"guid": "084310a5-0672-471b-a77e-bb3ecf733500","wall_id": 43,"group_id": 1,"status": 1,"super_admin": 0,"username": "davidrider","email": "davidrider@uwc4c.com","auth_mode": "local","tags": null,"language": null,"last_activity_email": "2015-05-21 22:34:44","created_at": "2015-05-21 22:34:44","created_by": 26,"updated_at": "2015-05-21 22:34:44","updated_by": 26,"last_login": "2015-05-21 22:35:26","visibility": 1}, {"id": 33,"guid": "77605395-aae0-41a8-95df-4da533a04580","wall_id": 44,"group_id": 1,"status": 1,"super_admin": 0,"username": "lunilibes","email": "lunilibes@uwc4c.com","auth_mode": "local","tags": null,"language": null,"last_activity_email": "2015-05-21 22:43:48","created_at": "2015-05-21 22:43:48","created_by": 26,"updated_at": "2015-05-21 22:46:05","updated_by": 33,"last_login": "2015-05-21 22:44:26","visibility": 1}, {"id": 34,"guid": "0347fd79-60dd-40af-bbcf-ee9346b93e61","wall_id": 45,"group_id": 1,"status": 1,"super_admin": 0,"username": "crystaljones","email": "crystaljones@uwc4c.com","auth_mode": "local","tags": null,"language": null,"last_activity_email": "2015-05-21 22:52:41","created_at": "2015-05-21 22:52:41","created_by": 26,"updated_at": "2015-05-21 22:52:41","updated_by": 26,"last_login": "2015-05-21 22:54:49","visibility": 1}, {"id": 35,"guid": "763c760b-4000-4c45-bf9a-5d0a0403e843","wall_id": 46,"group_id": 1,"status": 1,"super_admin": 0,"username": "johntolomei","email": "johntolomei@uwc4c.com","auth_mode": "local","tags": null,"language": null,"last_activity_email": "2015-05-21 23:11:29","created_at": "2015-05-21 23:11:29","created_by": 26,"updated_at": "2015-05-21 23:11:29","updated_by": 26,"last_login": "2015-05-21 23:11:43","visibility": 1}, {"id": 36,"guid": "4d296281-a665-413e-a178-6d283f4e4ac6","wall_id": 47,"group_id": 1,"status": 1,"super_admin": 0,"username": "lizgruber","email": "luzgruber@uwc4c.com","auth_mode": "local","tags": null,"language": null,"last_activity_email": "2015-05-22 02:31:43","created_at": "2015-05-22 02:31:43","created_by": 26,"updated_at": "2015-05-22 02:31:43","updated_by": 26,"last_login": "2015-05-22 02:32:32","visibility": 1}, {"id": 37,"guid": "d643cf55-d8ad-4d6c-8bad-b6f46797feec","wall_id": 48,"group_id": 1,"status": 1,"super_admin": 0,"username": "javiergaravito","email": "javiergaravito@uwc4c.com","auth_mode": "local","tags": null,"language": null,"last_activity_email": "2015-05-22 04:41:47","created_at": "2015-05-22 04:41:47","created_by": 26,"updated_at": "2015-05-22 04:41:47","updated_by": 26,"last_login": "2015-05-22 04:41:56","visibility": 1}, {"id": 38,"guid": "f57ce8ac-d17f-408c-9e8a-435312817578","wall_id": 49,"group_id": 1,"status": 1,"super_admin": 0,"username": "chrisdevore","email": "chrisdevore@uwc4c.com","auth_mode": "local","tags": null,"language": null,"last_activity_email": "2015-05-22 04:49:30","created_at": "2015-05-22 04:49:30","created_by": 26,"updated_at": "2015-05-22 04:49:30","updated_by": 26,"last_login": "2015-05-22 04:50:03","visibility": 1}, {"id": 39,"guid": "be2cde03-5058-4862-b02e-893d83ae8a80","wall_id": 50,"group_id": 1,"status": 1,"super_admin": 0,"username": "briancrowley","email": "briancrowley@uwc4c.com","auth_mode": "local","tags": null,"language": null,"last_activity_email": "2015-05-22 04:55:40","created_at": "2015-05-22 04:55:40","created_by": 26,"updated_at": "2015-05-22 04:55:40","updated_by": 26,"last_login": "2015-05-22 04:56:00","visibility": 1}, {"id": 40,"guid": "a2672ced-57a9-4247-839c-d6de97d47e43","wall_id": 51,"group_id": 1,"status": 1,"super_admin": 0,"username": "josephwhitford","email": "josephwhitford@uwc4c.com","auth_mode": "local","tags": null,"language": null,"last_activity_email": "2015-05-22 05:05:35","created_at": "2015-05-22 05:05:35","created_by": 26,"updated_at": "2015-05-22 05:06:28","updated_by": 40,"last_login": "2015-05-22 05:06:07","visibility": 1}, {"id": 41,"guid": "1ffe0f76-8684-4940-b982-9348014eae0f","wall_id": 52,"group_id": 1,"status": 1,"super_admin": 0,"username": "pablosholman","email": "pablosholman@uwc4c.com","auth_mode": "local","tags": null,"language": null,"last_activity_email": "2015-05-22 05:22:43","created_at": "2015-05-22 05:22:43","created_by": 26,"updated_at": "2015-05-22 05:22:43","updated_by": 26,"last_login": "2015-05-22 05:24:36","visibility": 1}, {"id": 42,"guid": "d12cd56c-7a62-4067-9953-6dd732618a77","wall_id": 53,"group_id": 1,"status": 1,"super_admin": 0,"username": "wallacewhite","email": "wallacewhite@uwc4c.com","auth_mode": "local","tags": null,"language": null,"last_activity_email": "2015-05-22 05:34:59","created_at": "2015-05-22 05:34:59","created_by": 26,"updated_at": "2015-05-22 05:34:59","updated_by": 26,"last_login": "2015-05-22 05:35:11","visibility": 1}, {"id": 43,"guid": "0ad071b8-cf7d-445c-8d2e-f85c2a63194b","wall_id": 54,"group_id": 1,"status": 1,"super_admin": 0,"username": "diegooppenheimer","email": "diegooppenheimer@uwc4c.com","auth_mode": "local","tags": null,"language": null,"last_activity_email": "2015-05-22 17:01:39","created_at": "2015-05-22 17:01:39","created_by": 26,"updated_at": "2015-05-22 17:07:38","updated_by": 43,"last_login": "2015-05-22 19:39:07","visibility": 1}, {"id": 44,"guid": "77b2f181-660d-45dc-a114-eb26f0a63ca5","wall_id": 55,"group_id": 1,"status": 1,"super_admin": 0,"username": "jjx1996","email": "jijingxuan@126.com","auth_mode": "local","tags": null,"language": "en","last_activity_email": "2015-05-22 22:34:33","created_at": "2015-05-22 22:34:33","created_by": null,"updated_at": "2015-05-22 22:39:54","updated_by": 44,"last_login": "2015-05-22 22:36:07","visibility": 1}]
